setup.py
src/ore/__init__.py
src/ore.xd.egg-info/PKG-INFO
src/ore.xd.egg-info/SOURCES.txt
src/ore.xd.egg-info/dependency_links.txt
src/ore.xd.egg-info/namespace_packages.txt
src/ore.xd.egg-info/requires.txt
src/ore.xd.egg-info/top_level.txt
src/ore.xd.egg-info/zip-safe
src/ore/xd/__init__.py
src/ore/xd/_xd.py