Metadata-Version: 1.0
Name: ore.xd
Version: 0.5.0
Summary: A Python XML Serializer/Deserializer that allows marshalling of simple types.
